imoc/__init__.py
imoc/simple_image_classifier.py
imoc-0.0.1.dist-info/License.txt
imoc-0.0.1.dist-info/METADATA
imoc-0.0.1.dist-info/WHEEL
imoc-0.0.1.dist-info/top_level.txt
imoc-0.0.1.dist-info/RECORD
