Metadata-Version: 2.1
Name: imoc
Version: 0.0.1
Summary: Image classifier model that automate every steps in image classification
Author: Nikhil
Author-email: thalappallinikhil@gmail.com
License: MIT
Keywords: image detection,machine learning,computer visionn
Classifier: Development Status :: 1 - Planning
Classifier: Intended Audience :: Developers
Classifier: Programming Language :: Python
License-File: License.txt
Requires-Dist: tensorflow
Requires-Dist: opencv
Requires-Dist: matplotlib
Requires-Dist: numpy
Requires-Dist: imghdr
